mcp_12306/__init__.py
mcp_12306/__main__.py
mcp_12306/mcp_12306_server.py
mcp_12306/query_12306.py
mcp_12306/station.txt
mcp_12306-0.1.8.dist-info/METADATA
mcp_12306-0.1.8.dist-info/WHEEL
mcp_12306-0.1.8.dist-info/entry_points.txt
mcp_12306-0.1.8.dist-info/licenses/LICENSE
mcp_12306-0.1.8.dist-info/RECORD
