Metadata-Version: 2.4
Name: mcp_12306
Version: 0.1.8
Summary: A simple MCP server to query ticket information in 12306.
Author: Zheng Chenguang
Maintainer-email: Zheng Chenguang <zhengchenguang315@gmail.com>
License-File: LICENSE
Keywords: automation,llm,mcp
Requires-Python: >=3.10
Requires-Dist: aiohttp
Requires-Dist: anyio
Requires-Dist: build>=1.2.2.post1
Requires-Dist: click
Requires-Dist: httpx
Requires-Dist: mcp
Requires-Dist: mcp[cli]>=1.9.2
Requires-Dist: redis
Requires-Dist: twine>=6.1.0
